{
	"info": {
		"_postman_id": "4e953f1c-48c4-4814-9b4a-f067351b9dda",
		"name": "node-asana",
		"schema": "https://schema.getpostman.com/json/collection/v2.1.0/collection.json"
	},
	"item": [
		{
			"name": "List all projects",
			"request": {
				"method": "GET",
				"header": []
			},
			"response": []
		},
		{
			"name": "List all tasks by projectID",
			"request": {
				"method": "GET",
				"header": []
			},
			"response": []
		},
		{
			"name": "Mark task completion",
			"request": {
				"method": "GET",
				"header": []
			},
			"response": []
		}
	]
}